LICENSE
MANIFEST.in
README.rst
requirements.txt
setup.py
django_renderit.egg-info/PKG-INFO
django_renderit.egg-info/SOURCES.txt
django_renderit.egg-info/dependency_links.txt
django_renderit.egg-info/requires.txt
django_renderit.egg-info/top_level.txt
doc_src/Makefile
doc_src/conf.py
doc_src/getting_started.rst
doc_src/index.rst
doc_src/installation.rst
doc_src/make.bat
doc_src/settings.rst
doc_src/templatefallback.rst
doc_src/templatetags.rst
doc_src/_build/doctrees/environment.pickle
doc_src/_build/doctrees/getting_started.doctree
doc_src/_build/doctrees/index.doctree
doc_src/_build/doctrees/installation.doctree
doc_src/_build/doctrees/settings.doctree
doc_src/_build/doctrees/templatefallack.doctree
doc_src/_build/doctrees/templatefallback.doctree
doc_src/_build/doctrees/templatetags.doctree
doc_src/_build/doctrees/reference/index.doctree
doc_src/_build/doctrees/reference/settings.doctree
doc_src/_static/breadcrumb_background.png
doc_src/_static/default.css
doc_src/_static/documentation.png
doc_src/_static/header_sm_mid.png
doc_src/_static/scrn1.png
doc_src/_static/scrn2.png
doc_src/_static/searchfield_leftcap.png
doc_src/_static/searchfield_repeat.png
doc_src/_static/searchfield_rightcap.png
doc_src/_static/title_background.png
doc_src/_static/toc.js
doc_src/_static/triangle_closed.png
doc_src/_static/triangle_left.png
doc_src/_static/triangle_open.png
doc_src/_templates/layout.html
docs/.buildinfo
docs/genindex.html
docs/getting_started.html
docs/index.html
docs/installation.html
docs/objects.inv
docs/search.html
docs/searchindex.js
docs/settings.html
docs/templatefallback.html
docs/templatetags.html
docs/_sources/getting_started.txt
docs/_sources/index.txt
docs/_sources/installation.txt
docs/_sources/settings.txt
docs/_sources/templatefallack.txt
docs/_sources/templatefallback.txt
docs/_sources/templatetags.txt
docs/_sources/reference/index.txt
docs/_sources/reference/settings.txt
docs/_static/ajax-loader.gif
docs/_static/basic.css
docs/_static/breadcrumb_background.png
docs/_static/classic.css
docs/_static/comment-bright.png
docs/_static/comment-close.png
docs/_static/comment.png
docs/_static/default.css
docs/_static/doctools.js
