Metadata-Version: 1.1
Name: django-renderit
Version: 1.2
Summary: Application that can render any object
Home-page: http://github.com/jsoa/django-renderit/
Author: Jose Soares
Author-email: jose@linux.com
License: UNKNOWN
Platform: UNKNOWN
Classifier: Framework :: Django
Classifier: License :: OSI Approved :: Apache Software License
Classifier: Development Status :: 4 - Beta
Classifier: Environment :: Other Environment
Classifier: Programming Language :: Python
